openrainflow/__init__.py
openrainflow/damage.py
openrainflow/eurocode.py
openrainflow/parallel.py
openrainflow/rainflow.py
openrainflow/utils.py
openrainflow/visualization.py
openrainflow-1.0.0.dist-info/licenses/LICENSE
openrainflow-1.0.0.dist-info/METADATA
openrainflow-1.0.0.dist-info/WHEEL
openrainflow-1.0.0.dist-info/top_level.txt
openrainflow-1.0.0.dist-info/RECORD
