Metadata-Version: 2.4
Name: openrainflow
Version: 1.0.0
Summary: High-performance fatigue analysis package with rainflow counting, Eurocode fatigue curves, and Miner's damage calculation
Author: OpenRainflow Contributors
License: MIT
Project-URL: Homepage, https://github.com/Pavlishenku/OpenRainflow
Project-URL: Repository, https://github.com/Pavlishenku/OpenRainflow
Project-URL: Bug Tracker, https://github.com/Pavlishenku/OpenRainflow/issues
Classifier: Development Status :: 5 - Production/Stable
Classifier: Intended Audience :: Science/Research
Classifier: Intended Audience :: Developers
Classifier: License :: OSI Approved :: MIT License
Classifier: Programming Language :: Python :: 3
Classifier: Programming Language :: Python :: 3.8
Classifier: Programming Language :: Python :: 3.9
Classifier: Programming Language :: Python :: 3.10
Classifier: Programming Language :: Python :: 3.11
Classifier: Programming Language :: Python :: 3.12
Classifier: Topic :: Scientific/Engineering
Requires-Python: >=3.8
License-File: LICENSE
Requires-Dist: numpy>=1.20.0
Requires-Dist: numba>=0.56.0
Requires-Dist: scipy>=1.7.0
Provides-Extra: dev
Requires-Dist: pytest>=7.0.0; extra == "dev"
Requires-Dist: pytest-cov>=4.0.0; extra == "dev"
Requires-Dist: black>=22.0.0; extra == "dev"
Requires-Dist: flake8>=5.0.0; extra == "dev"
Requires-Dist: mypy>=0.990; extra == "dev"
Provides-Extra: parallel
Requires-Dist: joblib>=1.2.0; extra == "parallel"
Dynamic: license-file
